AUTHORS.rst
CONTRIBUTING.rst
HISTORY.rst
LICENSE
MANIFEST.in
README.rst
setup.cfg
setup.py
docs/Makefile
docs/authors.rst
docs/conf.py
docs/contributing.rst
docs/history.rst
docs/index.rst
docs/installation.rst
docs/make.bat
docs/readme.rst
docs/usage.rst
simplebst/__init__.py
simplebst/traversals.py
simplebst/utils.py
simplebst.egg-info/PKG-INFO
simplebst.egg-info/SOURCES.txt
simplebst.egg-info/dependency_links.txt
simplebst.egg-info/not-zip-safe
simplebst.egg-info/top_level.txt
tests/__init__.py
tests/test_simplebst.py
tests/simplebst/__init__.py
tests/simplebst/test_traversals.py
tests/simplebst/test_utils.py