Metadata-Version: 1.1
Name: simplebst
Version: 0.4.0
Summary: Simple Binary Search Tree is a simple implementation of a binary search tree
Home-page: https://github.com/drincruz/simplebst
Author: Adrian Cruz
Author-email: drincruz at gmail dot com
License: MIT
Keywords: simplebst
Platform: UNKNOWN
Classifier: Development Status :: 2 - Pre-Alpha
Classifier: Intended Audience :: Developers
Classifier: License :: OSI Approved :: MIT License
Classifier: Natural Language :: English
Classifier: Programming Language :: Python :: 2
Classifier: Programming Language :: Python :: 2.6
Classifier: Programming Language :: Python :: 2.7
Classifier: Programming Language :: Python :: 3
Classifier: Programming Language :: Python :: 3.3
Classifier: Programming Language :: Python :: 3.4
